LICENSE
README.md
pyproject.toml
setup.py
src/pyRDF.egg-info/PKG-INFO
src/pyRDF.egg-info/SOURCES.txt
src/pyRDF.egg-info/dependency_links.txt
src/pyRDF.egg-info/top_level.txt
src/pyRDF.egg-info/zip-safe
src/rdf/__init__.py
src/rdf/formats.py
src/rdf/graph.py
src/rdf/namespaces.py
src/rdf/terms.py
tests/test_nquads-star.py
tests/test_nquads.py
tests/test_ntriples-star.py
tests/test_ntriples.py