Metadata-Version: 2.4
Name: pyRDF
Version: 2.3.2
Summary: Lightweight RDF Stream Parser
Home-page: https://wxwilcke.gitlab.io/pyRDF
Download-URL: https://gitlab.com/wxwilcke/pyRDF/-/archive/2.3.2/pyRDF-2.3.2.tar.gz
Author: Xander Wilcke
Author-email: Xander Wilcke <w.x.wilcke@vu.nl>
License-Expression: GPL-3.0-or-later
Project-URL: Homepage, https://wxwilcke.gitlab.io/pyRDF
Project-URL: Bug Tracker, https://gitlab.com/wxwilcke/pyRDF/-/issues
Keywords: rdf,ntriples,nquads,rdf-star,parser,streamer
Classifier: Programming Language :: Python :: 3
Classifier: Operating System :: OS Independent
Requires-Python: >=3.8
License-File: LICENSE
Dynamic: author
Dynamic: download-url
Dynamic: home-page
Dynamic: license-file
Dynamic: requires-python
